artefacts_toolkit_config/__init__.py
artefacts_toolkit_config/config.py
artefacts_toolkit_config/constants.py
artefacts_toolkit_config/version.py
artefacts_toolkit_config-0.2.1.dist-info/METADATA
artefacts_toolkit_config-0.2.1.dist-info/WHEEL
artefacts_toolkit_config-0.2.1.dist-info/top_level.txt
artefacts_toolkit_config-0.2.1.dist-info/RECORD
