Metadata-Version: 2.4
Name: artefacts_toolkit_config
Version: 0.2.1
Author-email: TN <tomo@artefacts.com>
Project-URL: Homepage, https://github.com/art-e-fact/artefacts-toolkit-config
Project-URL: Bug Tracker, https://github.com/art-e-fact/artefacts-toolkit-config/issues
Classifier: Programming Language :: Python :: 3
Classifier: License :: OSI Approved :: Apache Software License
Classifier: Operating System :: OS Independent
Requires-Python: >=3.10
Provides-Extra: dev
Requires-Dist: build; extra == "dev"
Requires-Dist: pyre-check; extra == "dev"
Requires-Dist: pytest; extra == "dev"
Requires-Dist: pytest-cov; extra == "dev"
Requires-Dist: pytest-env; extra == "dev"
Requires-Dist: pytest-mock; extra == "dev"
Requires-Dist: ruff; extra == "dev"
Requires-Dist: setuptools-scm; extra == "dev"
Requires-Dist: twine; extra == "dev"
